finterstellar/__init__.py
finterstellar/data_prep.py
finterstellar/financials.py
finterstellar/krx.py
finterstellar/local.py
finterstellar/trading.py
finterstellar/trend.py
finterstellar/visualization.py
finterstellar-0.3.2.dist-info/METADATA
finterstellar-0.3.2.dist-info/PKG-INFO 2
finterstellar-0.3.2.dist-info/WHEEL
finterstellar-0.3.2.dist-info/top_level.txt
finterstellar-0.3.2.dist-info/RECORD
