Metadata-Version: 2.1
Name: finterstellar
Version: 0.3.2
Summary: Quantitative analysis tools for investment
Home-page: https://github.com/finterstellar/library
Author: finterstellar
Author-email: finterstellar@naver.com
Classifier: Programming Language :: Python :: 3
Classifier: License :: OSI Approved :: MIT License
Classifier: Operating System :: OS Independent
Requires-Python: >=3.5
Requires-Dist: lxml >=4.2.6
Requires-Dist: numpy >=1.19.3
Requires-Dist: pandas >=1.1.4
Requires-Dist: requests >=2.23.0
Requires-Dist: matplotlib >=3.8.3
